{
    "indexDocs": {
        "1": {
            "Fichier": "corpusExamenCorrige/initiaux/2002-07-MOTCHANE-16708.txt",
            "Titre": "DROIT DES BREVETS OU DROIT À LA SANTÉ"
        },
        "2": {
            "Fichier": "corpusExamenCorrige/initiaux/103558-article.txt",
            "Titre": "AFRICA : EXTERNAL INTEREST AND INTERNAL INSECURITY "
        },
        "3": {
            "Fichier": "corpusExamenCorrige/initiaux/2002-02-BEILIN-16167.txt",
            "Titre": "OFFENSIVE CONCERTÉE CONTRE LES PALESTINIENS"
        },
        "4": {
            "Fichier": "corpusExamenCorrige/initiaux/103433-article.txt",
            "Titre": "THREATS TO DISARMAMENT AND INTERNATIONAL SECURITY"
        },
        "5": {
            "Fichier": "corpusExamenCorrige/initiaux/2001-08-FRANK-15516.txt",
            "Titre": "PARADIS DE BANLIEUE, VERSION AMÉRICAINE"
        },
        "6": {
            "Fichier": "corpusExamenCorrige/initiaux/2003-01-SERVANT-9856.txt",
            "Titre": "UNE PRIORITÉ GÉOSTRATÉGIQUE"
        },
        "7": {
            "Fichier": "corpusExamenCorrige/initiaux/2002-03-WARDE-16195.txt",
            "Titre": "CADRES ET EMPLOYÉS COMMUNIENT DANS LA « RELIGION » DU TRAVAIL"
        },
        "8": {
            "Fichier": "corpusExamenCorrige/initiaux/2002-07-CONESA-16699.txt",
            "Titre": "REMISE EN QUESTION DES TRAITÉS DE DÉSARMEMENT"
        },
        "9": {
            "Fichier": "corpusExamenCorrige/initiaux/2001-08-HALIMI-15544.txt",
            "Titre": "À QUAND LA TRANSPARENCE DANS LES MÉDIAS"
        },
        "10": {
            "Fichier": "corpusExamenCorrige/initiaux/2003-03-RAMONET-9870.txt",
            "Titre": "De la guerre perpétuelle"
        },
        "11": {
            "Fichier": "corpusExamenCorrige/initiaux/2003-01-KAPELIOUK-9652.txt",
            "Titre": "PARADOXES D'UN SCRUTIN"
        },
        "12": {
            "Fichier": "corpusExamenCorrige/initiaux/103557-article.txt",
            "Titre": "WHY THE LEFT IS ISRAEL'S ONLY HOPE FOR PEACE "
        },
        "13": {
            "Fichier": "corpusExamenCorrige/initiaux/103307-article.txt",
            "Titre": "THE VALE OF SORROWS "
        },
        "14": {
            "Fichier": "corpusExamenCorrige/initiaux/2002-03-JOHNSON-16293.txt",
            "Titre": "LES IMPASSES D'UN MODÈLE"
        },
        "15": {
            "Fichier": "corpusExamenCorrige/initiaux/103200-article.txt",
            "Titre": "ISRAEL VERSUS PALESTINE VERSUS THE WORLD"
        },
        "16": {
            "Fichier": "corpusExamenCorrige/initiaux/103455-article.txt",
            "Titre": "HEALTH FOR ALL OR RICHES FOR SOME"
        },
        "17": {
            "Fichier": "corpusExamenCorrige/initiaux/103060-article.txt",
            "Titre": "THE PRICE OF EU ACCESSION"
        },
        "18": {
            "Fichier": "corpusExamenCorrige/initiaux/103167-article.txt",
            "Titre": "AMERICAN BURBS "
        },
        "19": {
            "Fichier": "corpusExamenCorrige/initiaux/2002-03-ALGAZY-16302.txt",
            "Titre": "RELANCE DU MOUVEMENT PACIFISTE"
        },
        "20": {
            "Fichier": "corpusExamenCorrige/initiaux/2002-01-PARINGAUX-16015.txt",
            "Titre": "INDE ET PAKISTAN FACE À FACE"
        },
        "21": {
            "Fichier": "corpusExamenCorrige/initiaux/103342-article.txt",
            "Titre": "INSECURE, EXASPERATED AND BORED WITH THE OLD POLITICS "
        },
        "22": {
            "Fichier": "corpusExamenCorrige/initiaux/2001-01-DRWESKI-14685.txt",
            "Titre": "AU SEUIL D'UNE ADHÉSION COÛTEUSE"
        },
        "23": {
            "Fichier": "corpusExamenCorrige/initiaux/103310-article.txt",
            "Titre": "A PARTNER FOR THE FUTURE"
        },
        "24": {
            "Fichier": "corpusExamenCorrige/initiaux/2001-09-DE_LA_GORCE-15631.txt",
            "Titre": "LA PAIX MANQUÉE"
        },
        "25": {
            "Fichier": "corpusExamenCorrige/initiaux/103168-article.txt",
            "Titre": "MEDIA OWNERSHIP AND BIAS"
        },
        "26": {
            "Fichier": "corpusExamenCorrige/initiaux/103448-article.txt",
            "Titre": "THE FUTURE OF A MARGINALISED CONTINENT "
        },
        "27": {
            "Fichier": "corpusExamenCorrige/initiaux/103344-article.txt",
            "Titre": "THE PEACE MOVEMENT REVIVAL "
        },
        "28": {
            "Fichier": "corpusExamenCorrige/initiaux/103358-article.txt",
            "Titre": "END OF THE NEW WORKPLACE "
        },
        "29": {
            "Fichier": "corpusExamenCorrige/initiaux/2002-07-TSHIYEMBE-16697.txt",
            "Titre": "DU MESSIANISME AUX RIVES DE LA MONDIALISATION"
        },
        "30": {
            "Fichier": "corpusExamenCorrige/initiaux/103674-article.txt",
            "Titre": "GLOBAL CRISIS OVER IRAQ"
        }
    },
    "indexDocs_complémentaires": {
        "31": {
            "Fichier": "corpusExamenCorrige/complémentaires/103687-article.txt",
            "Titre": "COLLATERAL DAMAGE FROM AN ILLEGAL WAR"
        },
        "32": {
            "Fichier": "corpusExamenCorrige/complémentaires/2003-04-LAURENS-10112.txt",
            "Titre": "LES RAVAGES D'UNE GUERRE ARBITRAIRE"
        }
    }
}